asfamcparser.py
asfamc_parser-0.0.2.dist-info/LICENSE.txt
asfamc_parser-0.0.2.dist-info/METADATA
asfamc_parser-0.0.2.dist-info/WHEEL
asfamc_parser-0.0.2.dist-info/top_level.txt
asfamc_parser-0.0.2.dist-info/RECORD
