Metadata-Version: 2.1
Name: asfamc-parser
Version: 0.0.2
Summary: generic asf/amc parser following standard version 1.1.
Home-page: https://github.com/UomoCaffeLatte/PyAsfAmc
Author: Nikhil Reji
Author-email: Nikhil.Reji@live.co.uk
License: UNKNOWN
Platform: UNKNOWN
Classifier: Programming Language :: Python :: 3.6
Classifier: Programming Language :: Python :: 3.7
Classifier: License :: OSI Approved :: MIT License
Classifier: Natural Language :: English
Classifier: Topic :: Software Development :: Libraries
